django_boosted/__init__.py
django_boosted/apps.py
django_boosted/decorators.py
django_boosted/admin/__init__.py
django_boosted/admin/fieldsets.py
django_boosted/admin/format.py
django_boosted/admin/model.py
django_boosted/admin/tools.py
django_boosted/admin/urls.py
django_boosted/admin/views.py
django_boosted/admin/views_setup.py
django_boosted/managers/__init__.py
django_boosted/managers/urls.py
django_boosted/models/__init__.py
django_boosted/models/urls.py
django_boosted/rest_framework/__init__.py
django_boosted/rest_framework/metadata.py
django_boosted/templatetags/__init__.py
django_boosted/templatetags/boosted_tags.py
django_boosted-0.1.2.dist-info/licenses/LICENSE
django_boosted-0.1.2.dist-info/METADATA
django_boosted-0.1.2.dist-info/WHEEL
django_boosted-0.1.2.dist-info/top_level.txt
django_boosted-0.1.2.dist-info/RECORD
