Metadata-Version: 2.4
Name: django-boosted
Version: 0.1.2
Summary: Reusable helpers to register custom Django admin views and object tools.
Author-email: Hicinformatic <hicinformatic@gmail.com>
License: MIT
Project-URL: Homepage, https://github.com/hicinformatic/django-boosted
Project-URL: Repository, https://github.com/hicinformatic/django-boosted
Project-URL: Documentation, https://github.com/hicinformatic/django-boosted#readme
Project-URL: Issues, https://github.com/hicinformatic/django-boosted/issues
Keywords: django,django-admin,admin-views,admin-tools,django-extensions,admin-customization,python
Classifier: Framework :: Django
Classifier: Framework :: Django :: 4.2
Classifier: Framework :: Django :: 5.0
Classifier: Intended Audience :: Developers
Classifier: License :: OSI Approved :: MIT License
Classifier: Programming Language :: Python :: 3
Classifier: Programming Language :: Python :: 3.11
Classifier: Programming Language :: Python :: 3.12
Classifier: Programming Language :: Python :: 3 :: Only
Classifier: Topic :: Software Development :: Libraries :: Application Frameworks
Requires-Python: >=3.10
License-File: LICENSE
Requires-Dist: Django>=4.2
Provides-Extra: dev
Requires-Dist: pytest>=7.4; extra == "dev"
Requires-Dist: pytest-django>=4.8; extra == "dev"
Requires-Dist: ruff>=0.7.0; extra == "dev"
Requires-Dist: black>=24.8; extra == "dev"
Requires-Dist: bandit>=1.7; extra == "dev"
Requires-Dist: safety>=3.2; extra == "dev"
Requires-Dist: pip-audit>=2.7; extra == "dev"
Dynamic: license-file
